zope.browser-3.0-py3.9-nspkg.pth
zope/browser/README.rst
zope/browser/__init__.py
zope/browser/interfaces.py
zope/browser/tests.py
zope.browser-3.0.dist-info/LICENSE.txt
zope.browser-3.0.dist-info/METADATA
zope.browser-3.0.dist-info/WHEEL
zope.browser-3.0.dist-info/namespace_packages.txt
zope.browser-3.0.dist-info/top_level.txt
zope.browser-3.0.dist-info/RECORD
